setup.py
bale/__bale__.py
bale/__init__.py
bale/methods/__init__.py
balelib.egg-info/PKG-INFO
balelib.egg-info/SOURCES.txt
balelib.egg-info/dependency_links.txt
balelib.egg-info/top_level.txt